modm_data/__init__.py
modm_data/cube2kg/__init__.py
modm_data/cube2kg/__main__.py
modm_data/cubehal/__init__.py
modm_data/cubehal/dmamux_requests.py
modm_data/cubemx/__init__.py
modm_data/cubemx/device_data.py
modm_data/cubemx/peripherals.py
modm_data/cubemx/stm32_data.py
modm_data/dl/__init__.py
modm_data/dl/store.py
modm_data/dl/stmicro/__init__.py
modm_data/dl/stmicro/__main__.py
modm_data/dl/stmicro/cubemx.py
modm_data/dl/stmicro/cubeprog.py
modm_data/dl/stmicro/document.py
modm_data/dl/stmicro/data/cubemx.patch
modm_data/header2svd/__init__.py
modm_data/header2svd/header.py
modm_data/header2svd/stmicro/__init__.py
modm_data/header2svd/stmicro/__main__.py
modm_data/header2svd/stmicro/header.py
modm_data/header2svd/stmicro/tree.py
modm_data/html/__init__.py
modm_data/html/chapter.py
modm_data/html/document.py
modm_data/html/list.py
modm_data/html/parser.py
modm_data/html/table.py
modm_data/html/text.py
modm_data/html/stmicro/__init__.py
modm_data/html/stmicro/datasheet_sensor.py
modm_data/html/stmicro/datasheet_stm32.py
modm_data/html/stmicro/document.py
modm_data/html/stmicro/helper.py
modm_data/html/stmicro/reference.py
modm_data/html2owl/__init__.py
modm_data/html2owl/stmicro/__init__.py
modm_data/html2owl/stmicro/__main__.py
modm_data/html2svd/__init__.py
modm_data/html2svd/stmicro/__init__.py
modm_data/html2svd/stmicro/__main__.py
modm_data/html2svd/stmicro/datasheet.py
modm_data/html2svd/stmicro/reference.py
modm_data/kg/__init__.py
modm_data/kg/identifier.py
modm_data/kg/store.py
modm_data/kg/stmicro/__init__.py
modm_data/kg/stmicro/identifier.py
modm_data/kg/stmicro/model.py
modm_data/kg/stmicro/schema.py
modm_data/pdf/__init__.py
modm_data/pdf/character.py
modm_data/pdf/document.py
modm_data/pdf/image.py
modm_data/pdf/link.py
modm_data/pdf/page.py
modm_data/pdf/path.py
modm_data/pdf/render.py
modm_data/pdf/structure.py
modm_data/pdf2html/__init__.py
modm_data/pdf2html/ast.py
modm_data/pdf2html/cell.py
modm_data/pdf2html/convert.py
modm_data-0.0.3.dist-info/licenses/LICENSE
modm_data-0.0.3.dist-info/METADATA
modm_data-0.0.3.dist-info/WHEEL
modm_data-0.0.3.dist-info/top_level.txt
modm_data-0.0.3.dist-info/RECORD
