Metadata-Version: 2.4
Name: modm-data
Version: 0.0.3
Summary: Embedded Hardware Description Processor
Author-email: Niklas Hauser <niklas@salkinium.com>
License: MPL-2.0
Project-URL: Homepage, https://data.modm.io
Project-URL: API Docs, https://data.modm.io/api
Project-URL: GitHub, https://github.com/modm-io/modm-data
Project-URL: Changelog, https://github.com/modm-io/modm-data/blob/main/CHANGELOG.md
Keywords: embedded,hardware,pdf,parser
Classifier: Development Status :: 4 - Beta
Classifier: Environment :: Console
Classifier: Intended Audience :: Developers
Classifier: License :: OSI Approved :: Mozilla Public License 2.0 (MPL 2.0)
Classifier: Operating System :: Unix
Classifier: Programming Language :: Python :: 3.11
Classifier: Topic :: Database
Classifier: Topic :: Documentation
Classifier: Topic :: Scientific/Engineering :: Information Analysis
Classifier: Topic :: Software Development :: Documentation
Classifier: Topic :: Software Development :: Embedded Systems
Requires-Python: >=3.11
License-File: LICENSE
Requires-Dist: anytree==2.12.1
Requires-Dist: CppHeaderParser<3,>=2.7.4
Requires-Dist: jinja2<4,>=3.1.3
Requires-Dist: lxml<6,>=5.2.0
Requires-Dist: kuzu<0.12,>=0.11.3
Requires-Dist: pypdfium2==4.30.0
Requires-Dist: tqdm<5,>=4.66.2
Provides-Extra: docs
Requires-Dist: pdoc<15,>=14; extra == "docs"
Requires-Dist: mkdocs<2,>=1.5; extra == "docs"
Requires-Dist: mkdocs-material<10,>=9.5; extra == "docs"
Provides-Extra: all
Requires-Dist: modm_data[docs]; extra == "all"
Dynamic: license-file
